MANIFEST.in
README.rst
setup.py
DAD.egg-info/PKG-INFO
DAD.egg-info/SOURCES.txt
DAD.egg-info/dependency_links.txt
DAD.egg-info/requires.txt
DAD.egg-info/top_level.txt
dad/__init__.py
dad/event.py
dad/mom.py