Metadata-Version: 1.1
Name: DAD
Version: 1.0.2
Summary: Deliver Asynchronous Data
Home-page: http://github.com/globocom/dad
Author: Globo.com
Author-email: semantica@corp.globo.com
License: GNU GPLv2
Download-URL: https://pypi.python.org/pypi/DAD
Platform: UNKNOWN
Classifier: Development Status :: 5 - Production/Stable
Classifier: Environment :: Web Environment
Classifier: Intended Audience :: Developers
Classifier: Operating System :: OS Independent
Classifier: Programming Language :: Python
